__init__.py
document_model.py
napstech_models-1.0.0.dist-info/licenses/LICENSE
napstech_models-1.0.0.dist-info/METADATA
napstech_models-1.0.0.dist-info/WHEEL
napstech_models-1.0.0.dist-info/top_level.txt
napstech_models-1.0.0.dist-info/RECORD
