Metadata-Version: 2.4
Name: napstech_models
Version: 1.0.0
Summary: model packages for precisetax
Author-email: napstechnologies <ashish@napstechnologies.com>
Project-URL: Homepage, https://github.com/pypa/sampleproject
Project-URL: Issues, https://github.com/pypa/sampleproject/issues
Classifier: Programming Language :: Python :: 3
Classifier: Operating System :: OS Independent
Classifier: License :: OSI Approved :: MIT License
Requires-Python: >=3.8
License-File: LICENSE
Dynamic: license-file
